{
    "os": "Windows-10-10.0.22000-SP0",
    "python": "3.8.12",
    "heartbeatAt": "2021-11-26T18:02:32.373919",
    "startedAt": "2021-11-26T18:02:29.755254",
    "docker": null,
    "gpu": "NVIDIA GeForce GTX 1650 Ti",
    "gpu_count": 1,
    "cpu_count": 12,
    "cuda": null,
    "args": [
        "--ip=127.0.0.1",
        "--stdin=9003",
        "--control=9001",
        "--hb=9000",
        "--Session.signature_scheme=\"hmac-sha256\"",
        "--Session.key=b\"c0d8502b-5fb5-45e3-aa7a-eef01ecd20ba\"",
        "--shell=9002",
        "--transport=\"tcp\"",
        "--iopub=9004",
        "--f=C:\\Users\\ADMIN\\AppData\\Local\\Temp\\tmp-2788Kyb6Yct6WBRm.json"
    ],
    "state": "running",
    "program": "<python with no main file>",
    "git": {
        "remote": "https://github.com/rk2896/MLOps_project.git",
        "commit": "16799a3f9aa67fb024393b2e4e9f8ef281bfc594"
    },
    "email": "rahav.manoharan20@iimb.ac.in",
    "root": "C:/Users/ADMIN/Desktop/Rahav/IIMB/Term5/MLOps/project/MLOps_project",
    "host": "LAPTOP-GES64T0T",
    "username": "ADMIN",
    "executable": "C:\\Users\\ADMIN\\.conda\\envs\\mlopslab\\python.exe"
}
